glyphsh/glyph_view.py
glyphsh/main.py
glyphsh-1.1.0.dist-info/licenses/LICENSE
glyphsh-1.1.0.dist-info/METADATA
glyphsh-1.1.0.dist-info/WHEEL
glyphsh-1.1.0.dist-info/entry_points.txt
glyphsh-1.1.0.dist-info/top_level.txt
glyphsh-1.1.0.dist-info/RECORD
