Metadata-Version: 2.4
Name: glyphsh
Version: 1.1.0
Summary: Social media reinvented. In a terminal.
Author-email: pizzalover125 <chessthinker600@gmail.com>
Project-URL: main page, https://glyph-sh.vercel.app/
Project-URL: github, https://github.com/pizzalover125/glyph
Requires-Python: <3.13,>=3.10
License-File: LICENSE
Requires-Dist: rich>=13.0.0
Requires-Dist: questionary>=2.0.0
Requires-Dist: requests>=2.31.0
Dynamic: license-file
